epidtool/__init__.py
epidtool/_version.py
epidtool/beta_models.py
epidtool/compartmental_models.py
epidtool/estimate_r.py
epidtool/estimate_tc.py
epidtool/growth_models.py
epidtool/models.py
epidtool/optimizer.py
epidtool/table.py
epidtool/utils.py
epidtool-0.0.4.dist-info/LICENSE
epidtool-0.0.4.dist-info/METADATA
epidtool-0.0.4.dist-info/WHEEL
epidtool-0.0.4.dist-info/top_level.txt
epidtool-0.0.4.dist-info/RECORD
