Metadata-Version: 2.1
Name: epidtool
Version: 0.0.4
Summary: A Python toolkit for analysis, modelling and forecasting Epidemic
Home-page: https://github.com/souvikmanik/Pandemicpy
Author: Souvik Manik
Author-email: smanik.astro@gmail.com
Classifier: Programming Language :: Python :: 3
Classifier: License :: OSI Approved :: MIT License
Classifier: Operating System :: OS Independent
Requires-Python: >=3.8
License-File: LICENSE
Requires-Dist: numpy
Requires-Dist: scipy
Requires-Dist: scikit-learn (==1.0.2)
Requires-Dist: statsmodels (==0.13.2)
Requires-Dist: pandas
Requires-Dist: setuptools (==69.0.2)
